LICENSE
MANIFEST.in
README.md
requirements.txt
setup.cfg
setup.py
wagtail_blocks/__init__.py
wagtail_blocks/blocks.py
wagtail_blocks/test_dummy.py
wagtail_blocks/wagtail_hooks.py
wagtail_blocks.egg-info/PKG-INFO
wagtail_blocks.egg-info/SOURCES.txt
wagtail_blocks.egg-info/dependency_links.txt
wagtail_blocks.egg-info/requires.txt
wagtail_blocks.egg-info/top_level.txt
wagtail_blocks/static/wagtail_blocks/bootstrap.min.css
wagtail_blocks/static/wagtail_blocks/cropped_images_with_text.css
wagtail_blocks/static/wagtail_blocks/image_slider.css
wagtail_blocks/static/wagtail_blocks/image_text_overlay.css
wagtail_blocks/static/wagtail_blocks/list_with_images.css
wagtail_blocks/static/wagtail_blocks/js/Chart.bundle.min.js
wagtail_blocks/static/wagtail_blocks/js/bootstrap.bundle.min.js
wagtail_blocks/templates/wagtail_blocks/chart.html
wagtail_blocks/templates/wagtail_blocks/cropped_images_with_text.html
wagtail_blocks/templates/wagtail_blocks/header.html
wagtail_blocks/templates/wagtail_blocks/image_slider.html
wagtail_blocks/templates/wagtail_blocks/image_text_overlay.html
wagtail_blocks/templates/wagtail_blocks/list.html
wagtail_blocks/templates/wagtail_blocks/list_with_images.html
wagtail_blocks/templates/wagtail_blocks/map.html
wagtail_blocks/templates/wagtail_blocks/thumbnail_gallery.html
wagtail_blocks/templates/wagtail_blocks/admin_blocks/map.html
wagtail_blocks/templatetags/__init__.py
wagtail_blocks/templatetags/wagtail_html_support.py