Metadata-Version: 2.1
Name: wagtail-blocks
Version: 1.0.1
Summary: A Collection of awesome Wagtail CMS stream-field blocks and Charts
Home-page: https://github.com/ibrahimawadhamid/wagtail_blocks/
Author: IbrahimAwadHamid
Author-email: ibrahim.a.hamid@gmail.com
License: MIT
Keywords: WAGTAIL,STREAMFIELD,WAGTAIL_BLOCKS,WAGTAIL CMS
Classifier: Development Status :: 5 - Production/Stable
Classifier: Environment :: Web Environment
Classifier: Framework :: Django
Classifier: Framework :: Django :: 3.2
Classifier: Framework :: Django :: 4.1
Classifier: Framework :: Django :: 4.2
Classifier: Framework :: Wagtail
Classifier: Framework :: Wagtail :: 4
Classifier: Framework :: Wagtail :: 5
Classifier: Intended Audience :: Developers
Classifier: License :: OSI Approved :: MIT License
Classifier: Operating System :: OS Independent
Classifier: Programming Language :: Python
Classifier: Programming Language :: Python :: 3.8
Classifier: Programming Language :: Python :: 3.9
Classifier: Programming Language :: Python :: 3.10
Classifier: Programming Language :: Python :: 3.11
Classifier: Topic :: Internet :: WWW/HTTP
Classifier: Topic :: Internet :: WWW/HTTP :: Dynamic Content
Classifier: Topic :: Software Development
Provides-Extra: testing
Provides-Extra: docs
License-File: LICENSE
